[
    {

      "typeInstallation": "60e72dfb5d2c12c7449be001",
      "commune": "60e83f9a4f7d3bc8592ae001",
      "levage": true,
      "nacelle": false,
      "traveauxAnnexeConformite": true,
      "typeToiture": "toles",
      "ToitureTholeType": "ondulee"
    },
    {
  
      "typeInstallation": "60e72dfb5d2c12c7449be002",
      "commune": "60e83f9a4f7d3bc8592ae002",
      "levage": false,
      "nacelle": true,
      "traveauxAnnexeConformite": false,
      "typeToiture": "isotechnique",
      "ToitureIsotechniqueType": "ondulee"
    }
  ]
  